<gmi:MI_Metadata xmlns:gmi="http://www.isotc211.org/2005/gmi" xmlns:gco="http://www.isotc211.org/2005/gco" xmlns:gmd="http://www.isotc211.org/2005/gmd" xmlns:gml="http://www.opengis.net/gml/3.2" xmlns:gmx="http://www.isotc211.org/2005/gmx" xmlns:gsr="http://www.isotc211.org/2005/gsr" xmlns:gss="http://www.isotc211.org/2005/gss" xmlns:gts="http://www.isotc211.org/2005/gts" xmlns:xlink="http://www.w3.org/1999/xlink" xmlns:xsi="http://www.w3.org/2001/XMLSchema-instance" xsi:schemaLocation="http://www.isotc211.org/2005/gmi http://www.ngdc.noaa.gov/metadata/published/xsd/schema.xsd">
  <gmd:language>
    <gco:CharacterString>eng; USA</gco:CharacterString>
  </gmd:language>
  <gmd:characterSet>
    <gmd:MD_CharacterSetCode codeList="http://www.ngdc.noaa.gov/metadata/published/xsd/schema/resources/Codelist/gmxCodelists.xml#MD_CharacterSetCode" codeListValue="utf8">utf8</gmd:MD_CharacterSetCode>
  </gmd:characterSet>
  <gmd:hierarchyLevel>
    <gmd:MD_ScopeCode codeList="http://www.ngdc.noaa.gov/metadata/published/xsd/schema/resources/Codelist/gmxCodelists.xml#MD_ScopeCode" codeListValue="dataset">dataset</gmd:MD_ScopeCode>
  </gmd:hierarchyLevel>
  <gmd:contact>
    <gmd:CI_ResponsibleParty>
      <gmd:individualName>
        <gco:CharacterString>Tilton Margaret</gco:CharacterString>
      </gmd:individualName>
      <gmd:organisationName>
        <gco:CharacterString>DOC/NOAA/NESDIS/NCEI &gt; National Centers for Environmental Information, NESDIS, NOAA, U.S. Department of Commerce</gco:CharacterString>
      </gmd:organisationName>
      <gmd:positionName>
        <gco:CharacterString>Data Manager</gco:CharacterString>
      </gmd:positionName>
      <gmd:contactInfo>
        <gmd:CI_Contact>
          <gmd:phone>
            <gmd:CI_Telephone>
              <gmd:voice>
                <gco:CharacterString>303-497-6223</gco:CharacterString>
              </gmd:voice>
            </gmd:CI_Telephone>
          </gmd:phone>
          <gmd:address>
            <gmd:CI_Address>
              <gmd:electronicMailAddress>
                <gco:CharacterString>goesr.spaceweatherdata@noaa.gov</gco:CharacterString>
              </gmd:electronicMailAddress>
            </gmd:CI_Address>
          </gmd:address>
        </gmd:CI_Contact>
      </gmd:contactInfo>
      <gmd:role>
        <gmd:CI_RoleCode codeList="http://www.ngdc.noaa.gov/metadata/published/xsd/schema/resources/Codelist/gmxCodelists.xml#CI_RoleCode" codeListValue="distributor">distributor</gmd:CI_RoleCode>
      </gmd:role>
    </gmd:CI_ResponsibleParty>
  </gmd:contact>
  <gmd:dateStamp>
    <gco:Date>2018-05-29</gco:Date>
  </gmd:dateStamp>
  <gmd:metadataStandardName>
    <gco:CharacterString>ISO 19115-2 Geographic Information - Metadata - Part 2: Extensions for Imagery and Gridded Data</gco:CharacterString>
  </gmd:metadataStandardName>
  <gmd:metadataStandardVersion>
    <gco:CharacterString>ISO 19115-2:2009(E)</gco:CharacterString>
  </gmd:metadataStandardVersion>
  <gmd:identificationInfo>
    <gmd:MD_DataIdentification>
      <gmd:citation>
        <gmd:CI_Citation>
          <gmd:title>
            <gco:CharacterString>GOES-R Series Level 2 SEISS Magnetospheric Particle Sensor High Energy (MPS-HI) Averages Product in Daily Aggregations</gco:CharacterString>
          </gmd:title>
          <gmd:alternateTitle>
            <gco:CharacterString>GOES-R L2 SEISS MPS-HI Averages in Daily Aggregations</gco:CharacterString>
          </gmd:alternateTitle>
          <gmd:date>
            <gmd:CI_Date>
              <gmd:date>
                <gco:Date>2018-05-29</gco:Date>
              </gmd:date>
              <gmd:dateType>
                <gmd:CI_DateTypeCode codeList="http://www.ngdc.noaa.gov/metadata/published/xsd/schema/resources/Codelist/gmxCodelists.xml#CI_DateTypeCode" codeListValue="publication">publication</gmd:CI_DateTypeCode>
              </gmd:dateType>
            </gmd:CI_Date>
          </gmd:date>
          <gmd:edition>
            <gco:CharacterString>1.0.0</gco:CharacterString>
          </gmd:edition>
          <gmd:citedResponsibleParty>
            <gmd:CI_ResponsibleParty>
              <gmd:organisationName>
                <gco:CharacterString>DOC/NOAA/NESDIS/NCEI &gt; National Centers for Environmental Information, NESDIS, NOAA, U.S. Department of Commerce</gco:CharacterString>
              </gmd:organisationName>
              <gmd:role>
                <gmd:CI_RoleCode codeList="http://www.ngdc.noaa.gov/metadata/published/xsd/schema/resources/Codelist/gmxCodelists.xml#CI_RoleCode" codeListValue="publisher">publisher</gmd:CI_RoleCode>
              </gmd:role>
            </gmd:CI_ResponsibleParty>
          </gmd:citedResponsibleParty>
          <gmd:citedResponsibleParty>
            <gmd:CI_ResponsibleParty>
              <gmd:organisationName>
                <gco:CharacterString>DOC/NOAA/NESDIS/NCEI &gt; National Centers for Environmental Information, NESDIS, NOAA, U.S. Department of Commerce</gco:CharacterString>
              </gmd:organisationName>
              <gmd:contactInfo>
                <gmd:CI_Contact>
                  <gmd:phone>
                    <gmd:CI_Telephone>
                      <gmd:voice>
                        <gco:CharacterString>3038188461</gco:CharacterString>
                      </gmd:voice>
                    </gmd:CI_Telephone>
                  </gmd:phone>
                  <gmd:address>
                    <gmd:CI_Address>
                      <gmd:electronicMailAddress>
                        <gco:CharacterString>goesr.seiss@noaa.gov</gco:CharacterString>
                      </gmd:electronicMailAddress>
                    </gmd:CI_Address>
                  </gmd:address>
                </gmd:CI_Contact>
              </gmd:contactInfo>
              <gmd:role>
                <gmd:CI_RoleCode codeList="http://www.ngdc.noaa.gov/metadata/published/xsd/schema/resources/Codelist/gmxCodelists.xml#CI_RoleCode" codeListValue="author">author</gmd:CI_RoleCode>
              </gmd:role>
            </gmd:CI_ResponsibleParty>
          </gmd:citedResponsibleParty>
          <gmd:citedResponsibleParty>
            <gmd:CI_ResponsibleParty>
              <gmd:organisationName gco:nilReason="missing" />
              <gmd:contactInfo>
                <gmd:CI_Contact>
                  <gmd:onlineResource>
                    <gmd:CI_OnlineResource>
                      <gmd:linkage>
                        <gmd:URL>https://www.ngdc.noaa.gov/stp/satellite/goes-r.html</gmd:URL>
                      </gmd:linkage>
                      <gmd:protocol>
                        <gco:CharacterString>HTTP</gco:CharacterString>
                      </gmd:protocol>
                      <gmd:applicationProfile>
                        <gco:CharacterString>Information</gco:CharacterString>
                      </gmd:applicationProfile>
                      <gmd:name>
                        <gco:CharacterString>GOES-R Space Weather Data Access Information Page</gco:CharacterString>
                      </gmd:name>
                      <gmd:description>
                        <gco:CharacterString>Website for information on GOES-R space weather data</gco:CharacterString>
                      </gmd:description>
                      <gmd:function>
                        <gmd:CI_OnLineFunctionCode codeList="http://www.ngdc.noaa.gov/metadata/published/xsd/schema/resources/Codelist/gmxCodelists.xml#CI_OnLineFunctionCode" codeListValue="information">information</gmd:CI_OnLineFunctionCode>
                      </gmd:function>
                    </gmd:CI_OnlineResource>
                  </gmd:onlineResource>
                </gmd:CI_Contact>
              </gmd:contactInfo>
              <gmd:role gco:nilReason="missing" />
            </gmd:CI_ResponsibleParty>
          </gmd:citedResponsibleParty>
          <gmd:presentationForm>
            <gmd:CI_PresentationFormCode codeList="http://www.ngdc.noaa.gov/metadata/published/xsd/schema/resources/Codelist/gmxCodelists.xml#CI_PresentationFormCode" codeListValue="tableDigital">tableDigital</gmd:CI_PresentationFormCode>
          </gmd:presentationForm>
        </gmd:CI_Citation>
      </gmd:citation>
      <gmd:abstract>
        <gco:CharacterString>The GOES-R Magnetospheric Electrons and Protons: Medium and High Energy (MPSH) averages consist of averaged fluxes of medium and high energy electrons and protons derived from in situ measurements of electron and proton count rates. Differential and integral electron fluxes are reported at eleven energy bands in five angular zones.  Ten of the energy bands are evenly spaced logarithmically spanning from 50 keV to 4 MeV with differential electron flux being reported. The eleventh energy band collects electrons with energies greater than 2 MeV with electron integral flux being reported. In addition, differential proton fluxes are reported at eleven energy bands in the same five angular zones. The eleven proton energy bands are evenly spaced logarithmically and range from 80 keV to 12 MeV.  Collectively, the five angular zones, each with a 30 degree field-of-view, span a total angular range of 170 degrees in the Y-Z arranged north to south with the central zone having an anti-earthward look-angle and are parallel to the minus Z-axis (in spacecraft body-reference-frame coordinates). With respect to the earth, the zones are arranged from north to south with the central zone pointing anti-earthward. In addition, the product contains ionizing radiation doses in two energy ranges, 50 keV to 1 MeV and 1 MeV to 10 MeV, obtained from a pair of Low and High Linear Energy Transfer dosimeters, respectively. 
In addition to observations, the averages products contain associated uncertainties and data quality flags. Averages are derived from Level 1b MPS-Hi files that contain observations at 1 Hz.</gco:CharacterString>
      </gmd:abstract>
      <gmd:purpose>
        <gco:CharacterString>The GOES-R Magnetospheric Electrons and Protons: Medium and High Energy (MPSH) Averages Product consists of averaged fluxes of medium and high energy electrons and protons derived from in situ measurements of electron and proton count rates. Differential and integral electron fluxes are reported at eleven energy bands in five angular zones. The data will help users who wish to monitor solar energetic particle (SEP) events and research magnetospheric conditions. 
NOAA's National Centers for Environmental Information (NCEI) produces these files by calculating averages from L1b input files.</gco:CharacterString>
      </gmd:purpose>
      <gmd:status>
        <gmd:MD_ProgressCode codeList="http://www.ngdc.noaa.gov/metadata/published/xsd/schema/resources/Codelist/gmxCodelists.xml#MD_ProgressCode" codeListValue="onGoing">onGoing</gmd:MD_ProgressCode>
      </gmd:status>
      <gmd:pointOfContact>
        <gmd:CI_ResponsibleParty>
          <gmd:individualName>
            <gco:CharacterString>Margaret Tilton</gco:CharacterString>
          </gmd:individualName>
          <gmd:organisationName>
            <gco:CharacterString>DOC/NOAA/NESDIS/NCEI &gt; National Centers for Environmental Information, NESDIS, NOAA, U.S. Department of Commerce</gco:CharacterString>
          </gmd:organisationName>
          <gmd:positionName>
            <gco:CharacterString>Data Manager</gco:CharacterString>
          </gmd:positionName>
          <gmd:contactInfo>
            <gmd:CI_Contact>
              <gmd:phone>
                <gmd:CI_Telephone>
                  <gmd:voice>
                    <gco:CharacterString>303-497-6223</gco:CharacterString>
                  </gmd:voice>
                </gmd:CI_Telephone>
              </gmd:phone>
              <gmd:address>
                <gmd:CI_Address>
                  <gmd:electronicMailAddress>
                    <gco:CharacterString>goesr.spaceweatherdata@noaa.gov</gco:CharacterString>
                  </gmd:electronicMailAddress>
                </gmd:CI_Address>
              </gmd:address>
            </gmd:CI_Contact>
          </gmd:contactInfo>
          <gmd:role>
            <gmd:CI_RoleCode codeList="http://www.ngdc.noaa.gov/metadata/published/xsd/schema/resources/Codelist/gmxCodelists.xml#CI_RoleCode" codeListValue="distributor">distributor</gmd:CI_RoleCode>
          </gmd:role>
        </gmd:CI_ResponsibleParty>
      </gmd:pointOfContact>
      <gmd:resourceMaintenance>
        <gmd:MD_MaintenanceInformation>
          <gmd:maintenanceAndUpdateFrequency>
            <gmd:MD_MaintenanceFrequencyCode codeList="http://www.ngdc.noaa.gov/metadata/published/xsd/schema/resources/Codelist/gmxCodelists.xml#MD_MaintenanceFrequencyCode" codeListValue="daily">daily</gmd:MD_MaintenanceFrequencyCode>
          </gmd:maintenanceAndUpdateFrequency>
        </gmd:MD_MaintenanceInformation>
      </gmd:resourceMaintenance>
      <gmd:resourceConstraints>
        <gmd:MD_Constraints>
          <gmd:useLimitation>
            <gco:CharacterString>These GOES-16 data are provisional and are still undergoing testing. Users receiving these data through any dissemination means assume all risk related to their use and NOAA disclaims any and all warranties, whether express or implied, including (without limitation) any implied warranties of merchantability or fitness for a particular purpose.</gco:CharacterString>
          </gmd:useLimitation>
        </gmd:MD_Constraints>
      </gmd:resourceConstraints>
      <gmd:resourceConstraints>
        <gmd:MD_LegalConstraints>
          <gmd:useConstraints>
            <gmd:MD_RestrictionCode codeList="http://www.ngdc.noaa.gov/metadata/published/xsd/schema/resources/Codelist/gmxCodelists.xml#MD_RestrictionCode" codeListValue="otherRestrictions">otherRestrictions</gmd:MD_RestrictionCode>
          </gmd:useConstraints>
          <gmd:otherConstraints>
            <gco:CharacterString>Cite this dataset when used as a source: GOES-R SEISS MPS-HI L2 Averages in Daily AggregationsNOAA National Centers for Environmental Information.</gco:CharacterString>
          </gmd:otherConstraints>
        </gmd:MD_LegalConstraints>
      </gmd:resourceConstraints>
      <gmd:resourceConstraints>
        <gmd:MD_LegalConstraints>
          <gmd:useConstraints>
            <gmd:MD_RestrictionCode codeList="http://www.ngdc.noaa.gov/metadata/published/xsd/schema/resources/Codelist/gmxCodelists.xml#MD_RestrictionCode" codeListValue="otherRestrictions">otherRestrictions</gmd:MD_RestrictionCode>
          </gmd:useConstraints>
          <gmd:otherConstraints>
            <gco:CharacterString>NCEI cannot assume liability for any damages caused by any errors or omissions in the data, nor as a result of the failure of the data to function on a particular system. NCEI makes no warranty, expressed or implied, nor does the fact of distribution constitute such a warranty. NCEI can only certify that the data it distributes are an authentic copy of the records that were accepted for inclusion in the NCEI archives.</gco:CharacterString>
          </gmd:otherConstraints>
        </gmd:MD_LegalConstraints>
      </gmd:resourceConstraints>
      <gmd:aggregationInfo>
        <gmd:MD_AggregateInformation>
          <gmd:aggregateDataSetName>
            <gmd:CI_Citation>
              <gmd:title>
                <gco:CharacterString>GOES-R Series Product Definition and User Guide (PUG)</gco:CharacterString>
              </gmd:title>
              <gmd:date gco:nilReason="missing" />
              <gmd:citedResponsibleParty>
                <gmd:CI_ResponsibleParty>
                  <gmd:organisationName>
                    <gco:CharacterString>GOES-R Program</gco:CharacterString>
                  </gmd:organisationName>
                  <gmd:role>
                    <gmd:CI_RoleCode codeList="http://www.ngdc.noaa.gov/metadata/published/xsd/schema/resources/Codelist/gmxCodelists.xml#CI_RoleCode" codeListValue="distributor">distributor</gmd:CI_RoleCode>
                  </gmd:role>
                </gmd:CI_ResponsibleParty>
              </gmd:citedResponsibleParty>
              <gmd:citedResponsibleParty>
                <gmd:CI_ResponsibleParty>
                  <gmd:organisationName gco:nilReason="missing" />
                  <gmd:contactInfo>
                    <gmd:CI_Contact>
                      <gmd:onlineResource>
                        <gmd:CI_OnlineResource>
                          <gmd:linkage>
                            <gmd:URL>http://www.goes-r.gov/users/docs/PUG-L1b-vol3.pdf</gmd:URL>
                          </gmd:linkage>
                          <gmd:protocol>
                            <gco:CharacterString>HTTP</gco:CharacterString>
                          </gmd:protocol>
                          <gmd:applicationProfile>
                            <gco:CharacterString>Web Browser</gco:CharacterString>
                          </gmd:applicationProfile>
                          <gmd:name>
                            <gco:CharacterString>GOES-R Series Product Definition and User Guide (PUG)</gco:CharacterString>
                          </gmd:name>
                          <gmd:description>
                            <gco:CharacterString>GOES-R Series PUG, Vol. 3 (L1b Products); describes high-resolution input files</gco:CharacterString>
                          </gmd:description>
                          <gmd:function>
                            <gmd:CI_OnLineFunctionCode codeList="http://www.ngdc.noaa.gov/metadata/published/xsd/schema/resources/Codelist/gmxCodelists.xml#CI_OnLineFunctionCode" codeListValue="information">information</gmd:CI_OnLineFunctionCode>
                          </gmd:function>
                        </gmd:CI_OnlineResource>
                      </gmd:onlineResource>
                    </gmd:CI_Contact>
                  </gmd:contactInfo>
                  <gmd:role gco:nilReason="missing" />
                </gmd:CI_ResponsibleParty>
              </gmd:citedResponsibleParty>
            </gmd:CI_Citation>
          </gmd:aggregateDataSetName>
          <gmd:associationType>
            <gmd:DS_AssociationTypeCode codeList="http://www.ngdc.noaa.gov/metadata/published/xsd/schema/resources/Codelist/gmxCodelists.xml#DS_AssociationTypeCode" codeListValue="crossReference">crossReference</gmd:DS_AssociationTypeCode>
          </gmd:associationType>
          <gmd:initiativeType>
            <gmd:DS_InitiativeTypeCode codeList="http://www.ngdc.noaa.gov/metadata/published/xsd/schema/resources/Codelist/gmxCodelists.xml#DS_InitiativeTypeCode" codeListValue="userGuide">userGuide</gmd:DS_InitiativeTypeCode>
          </gmd:initiativeType>
        </gmd:MD_AggregateInformation>
      </gmd:aggregationInfo>
      <gmd:language>
        <gco:CharacterString>eng; USA</gco:CharacterString>
      </gmd:language>
      <gmd:extent>
        <gmd:EX_Extent>
          <gmd:description>
            <gco:CharacterString>non-geographic dataset</gco:CharacterString>
          </gmd:description>
          <gmd:geographicElement gco:nilReason="inapplicable" />
          <gmd:temporalElement>
            <gmd:EX_TemporalExtent id="boundingTemporalExtent">
              <gmd:extent>
                <gml:TimePeriod gml:id="datasetTimePeriod">
                  <gml:description>ground condition</gml:description>
                  <gml:beginPosition>2018-05-29</gml:beginPosition>
                  <gml:endPosition indeterminatePosition="now" />
                </gml:TimePeriod>
              </gmd:extent>
            </gmd:EX_TemporalExtent>
          </gmd:temporalElement>
        </gmd:EX_Extent>
      </gmd:extent>
    </gmd:MD_DataIdentification>
  </gmd:identificationInfo>
  <gmd:distributionInfo>
    <gmd:MD_Distribution>
      <gmd:distributor>
        <gmd:MD_Distributor>
          <gmd:distributorContact>
            <gmd:CI_ResponsibleParty>
              <gmd:organisationName>
                <gco:CharacterString>DOC/NOAA/NESDIS/NCEI &gt; National Centers for Environmental Information, NESDIS, NOAA, U.S. Department of Commerce</gco:CharacterString>
              </gmd:organisationName>
              <gmd:positionName>
                <gco:CharacterString>General Contact</gco:CharacterString>
              </gmd:positionName>
              <gmd:contactInfo>
                <gmd:CI_Contact>
                  <gmd:phone>
                    <gmd:CI_Telephone>
                      <gmd:voice>
                        <gco:CharacterString>+1 303-497-6826</gco:CharacterString>
                      </gmd:voice>
                      <gmd:facsimile>
                        <gco:CharacterString>+1 303-497-6513</gco:CharacterString>
                      </gmd:facsimile>
                    </gmd:CI_Telephone>
                  </gmd:phone>
                  <gmd:address>
                    <gmd:CI_Address>
                      <gmd:deliveryPoint>
                        <gco:CharacterString>NOAA/NESDIS E/GC</gco:CharacterString>
                      </gmd:deliveryPoint>
                      <gmd:deliveryPoint>
                        <gco:CharacterString>325 Broadway</gco:CharacterString>
                      </gmd:deliveryPoint>
                      <gmd:city>
                        <gco:CharacterString>Boulder</gco:CharacterString>
                      </gmd:city>
                      <gmd:administrativeArea>
                        <gco:CharacterString>CO</gco:CharacterString>
                      </gmd:administrativeArea>
                      <gmd:postalCode>
                        <gco:CharacterString>80305-3328</gco:CharacterString>
                      </gmd:postalCode>
                      <gmd:country>
                        <gco:CharacterString>USA</gco:CharacterString>
                      </gmd:country>
                      <gmd:electronicMailAddress>
                        <gco:CharacterString>ngdc.info@noaa.gov</gco:CharacterString>
                      </gmd:electronicMailAddress>
                    </gmd:CI_Address>
                  </gmd:address>
                </gmd:CI_Contact>
              </gmd:contactInfo>
              <gmd:role>
                <gmd:CI_RoleCode codeList="http://www.ngdc.noaa.gov/metadata/published/xsd/schema/resources/Codelist/gmxCodelists.xml#CI_RoleCode" codeListValue="distributor">distributor</gmd:CI_RoleCode>
              </gmd:role>
            </gmd:CI_ResponsibleParty>
          </gmd:distributorContact>
          <gmd:distributionOrderProcess>
            <gmd:MD_StandardOrderProcess>
              <gmd:fees>
                <gco:CharacterString>Electronic downloads of the data are free, however fees may apply for data certifications and data distribution on physical media.</gco:CharacterString>
              </gmd:fees>
            </gmd:MD_StandardOrderProcess>
          </gmd:distributionOrderProcess>
          <gmd:distributorFormat>
            <gmd:MD_Format>
              <gmd:name>
                <gco:CharacterString>FITS</gco:CharacterString>
              </gmd:name>
              <gmd:version gco:nilReason="missing" />
            </gmd:MD_Format>
          </gmd:distributorFormat>
          <gmd:distributorTransferOptions>
            <gmd:MD_DigitalTransferOptions>
              <gmd:transferSize gco:nilReason="missing" />
            </gmd:MD_DigitalTransferOptions>
          </gmd:distributorTransferOptions>
        </gmd:MD_Distributor>
      </gmd:distributor>
    </gmd:MD_Distribution>
  </gmd:distributionInfo>
  <gmd:dataQualityInfo>
    <gmd:DQ_DataQuality>
      <gmd:scope>
        <gmd:DQ_Scope id="datasetScope">
          <gmd:level>
            <gmd:MD_ScopeCode codeList="http://www.ngdc.noaa.gov/metadata/published/xsd/schema/resources/Codelist/gmxCodelists.xml#MD_ScopeCode" codeListValue="dataset">dataset</gmd:MD_ScopeCode>
          </gmd:level>
          <gmd:extent xlink:href="#boundingExtent" />
        </gmd:DQ_Scope>
      </gmd:scope>
      <gmd:lineage>
        <gmd:LI_Lineage>
          <gmd:statement gco:nilReason="missing" />
        </gmd:LI_Lineage>
      </gmd:lineage>
    </gmd:DQ_DataQuality>
  </gmd:dataQualityInfo>
  <gmd:dataQualityInfo>
    <gmd:DQ_DataQuality>
      <gmd:scope>
        <gmd:DQ_Scope>
          <gmd:level>
            <gmd:MD_ScopeCode codeList="http://www.ngdc.noaa.gov/metadata/published/xsd/schema/resources/Codelist/gmxCodelists.xml#MD_ScopeCode" codeListValue="repository">repository</gmd:MD_ScopeCode>
          </gmd:level>
          <gmd:levelDescription>
            <gmd:MD_ScopeDescription>
              <gmd:other>
                <gco:CharacterString>NOAA National Centers for Environmental Information</gco:CharacterString>
              </gmd:other>
            </gmd:MD_ScopeDescription>
          </gmd:levelDescription>
        </gmd:DQ_Scope>
      </gmd:scope>
      <gmd:lineage>
        <gmd:LI_Lineage>
          <gmd:processStep>
            <gmi:LE_ProcessStep>
              <gmd:description>
                <gco:CharacterString>NOAA created the National Centers for Environmental Information (NCEI) by merging NOAA's National Climatic Data Center (NCDC), National Geophysical Data Center (NGDC), and National Oceanographic Data Center (NODC), including the National Coastal Data Development Center (NCDDC), per the Consolidated and Further Continuing Appropriations Act, 2015, Public Law 113-235. NCEI launched publicly on April 22, 2015.</gco:CharacterString>
              </gmd:description>
              <gmd:dateTime>
                <gco:DateTime>2015-04-22T00:00:00</gco:DateTime>
              </gmd:dateTime>
            </gmi:LE_ProcessStep>
          </gmd:processStep>
        </gmd:LI_Lineage>
      </gmd:lineage>
    </gmd:DQ_DataQuality>
  </gmd:dataQualityInfo>
  <gmd:metadataMaintenance>
    <gmd:MD_MaintenanceInformation>
      <gmd:maintenanceAndUpdateFrequency gco:nilReason="missing" />
    </gmd:MD_MaintenanceInformation>
  </gmd:metadataMaintenance>
</gmi:MI_Metadata>